autodyna/Autorun.py
autodyna/Beams.py
autodyna/Elastic_Beam.py
autodyna/Mat_Hys_Beam.py
autodyna/Shear_Calcs.py
autodyna/Shear_Calcs_Explicit.py
autodyna/__init__.py
autodyna/beamGeometry.py
autodyna/biLinearize.py
autodyna/construct_elasticBeams.py
autodyna/construct_hysBeams.py
autodyna/iXTRACT_envelope.py
autodyna/initialize.py
autodyna/inputs_elasticBeams.csv
autodyna/inputs_elasticBeams.txt
autodyna/inputs_elasticBeams.xlsx
autodyna/inputs_hysBeams.csv
autodyna/inputs_hysBeams.txt
autodyna/inputs_hysBeams.xlsx
autodyna/settings.py
autodyna/settings.txt
autodyna/util.py
autodyna/Array_Formatting/FormatForDYNA.xlsm
autodyna/Array_Formatting/ReadMe.md
autodyna/Resources/CSAshearTesting.py
autodyna/Resources/__init__.py
autodyna/Resources/XTRACT/GDI32.DLL
autodyna/Resources/XTRACT/SmallXTRACT.ico
autodyna/Resources/XTRACT/XTRACT.GID
autodyna/Resources/XTRACT/XTRACT.cnt
autodyna/Resources/XTRACT/XTRACT.exe
autodyna/Resources/XTRACT/__init__.py
autodyna/Resources/XTRACT/atl.dll
autodyna/Resources/XTRACT/checkKey.dll
autodyna/Resources/XTRACT/iai.key
autodyna-2.5.8.data/data/autodyna/inputs_elasticBeams.csv
autodyna-2.5.8.data/data/autodyna/inputs_elasticBeams.txt
autodyna-2.5.8.data/data/autodyna/inputs_elasticBeams.xlsx
autodyna-2.5.8.data/data/autodyna/inputs_hysBeams.csv
autodyna-2.5.8.data/data/autodyna/inputs_hysBeams.txt
autodyna-2.5.8.data/data/autodyna/inputs_hysBeams.xlsx
autodyna-2.5.8.data/data/autodyna/settings.txt
autodyna-2.5.8.data/data/autodyna/Array_Formatting/FormatForDYNA.xlsm
autodyna-2.5.8.data/data/autodyna/Array_Formatting/ReadMe.md
autodyna-2.5.8.data/data/autodyna/Resources/XTRACT/GDI32.DLL
autodyna-2.5.8.data/data/autodyna/Resources/XTRACT/SmallXTRACT.ico
autodyna-2.5.8.data/data/autodyna/Resources/XTRACT/XTRACT.GID
autodyna-2.5.8.data/data/autodyna/Resources/XTRACT/XTRACT.cnt
autodyna-2.5.8.data/data/autodyna/Resources/XTRACT/XTRACT.exe
autodyna-2.5.8.data/data/autodyna/Resources/XTRACT/atl.dll
autodyna-2.5.8.dist-info/LICENSE
autodyna-2.5.8.dist-info/METADATA
autodyna-2.5.8.dist-info/WHEEL
autodyna-2.5.8.dist-info/top_level.txt
autodyna-2.5.8.dist-info/RECORD
