Metadata-Version: 2.1
Name: autodyna
Version: 2.5.8
Summary: A collection of LS-DYNA card writing tools
Home-page: https://gitlab.arup.com/kevin.stanton/AutomatedCardGenerator_LS-DYNA
Author: Kevin Stanton
Author-email: kevin.stanton@arup.com
License: UNKNOWN
Platform: UNKNOWN
Requires-Dist: matplotlib
Requires-Dist: numpy
Requires-Dist: pywin32
Requires-Dist: pandas
Requires-Dist: datetime
Requires-Dist: psutil
Requires-Dist: scipy
